{
  "best_val_eer": 0.0,
  "test_eer": 0.0,
  "epochs": 50,
  "bonafide_clips": 50,
  "spoof_clips": 50,
  "history": [
    {
      "epoch": 1,
      "loss": 0.6122928500175476,
      "val_eer": 0.0
    },
    {
      "epoch": 2,
      "loss": 0.451523619890213,
      "val_eer": 0.0
    },
    {
      "epoch": 3,
      "loss": 0.3753189444541931,
      "val_eer": 0.0
    },
    {
      "epoch": 4,
      "loss": 0.2904639780521393,
      "val_eer": 0.0
    },
    {
      "epoch": 5,
      "loss": 0.24680640399456025,
      "val_eer": 0.0
    },
    {
      "epoch": 6,
      "loss": 0.18049755990505217,
      "val_eer": 0.0
    },
    {
      "epoch": 7,
      "loss": 0.12195878028869629,
      "val_eer": 0.0
    },
    {
      "epoch": 8,
      "loss": 0.09690268486738204,
      "val_eer": 0.0
    },
    {
      "epoch": 9,
      "loss": 0.07079961895942688,
      "val_eer": 0.0
    },
    {
      "epoch": 10,
      "loss": 0.07795481160283088,
      "val_eer": 0.0
    },
    {
      "epoch": 11,
      "loss": 0.04832578487694263,
      "val_eer": 0.0
    },
    {
      "epoch": 12,
      "loss": 0.03187279291450977,
      "val_eer": 0.0
    },
    {
      "epoch": 13,
      "loss": 0.022214648500084876,
      "val_eer": 0.0
    },
    {
      "epoch": 14,
      "loss": 0.03400939218699932,
      "val_eer": 0.0
    },
    {
      "epoch": 15,
      "loss": 0.015227870456874371,
      "val_eer": 0.0
    },
    {
      "epoch": 16,
      "loss": 0.027810875326395035,
      "val_eer": 0.0
    },
    {
      "epoch": 17,
      "loss": 0.018343456834554673,
      "val_eer": 0.0
    },
    {
      "epoch": 18,
      "loss": 0.018943721987307073,
      "val_eer": 0.0
    },
    {
      "epoch": 19,
      "loss": 0.012506934814155102,
      "val_eer": 0.0
    },
    {
      "epoch": 20,
      "loss": 0.012520552519708872,
      "val_eer": 0.0
    },
    {
      "epoch": 21,
      "loss": 0.009804798942059278,
      "val_eer": 0.0
    },
    {
      "epoch": 22,
      "loss": 0.010154158435761928,
      "val_eer": 0.0
    },
    {
      "epoch": 23,
      "loss": 0.007405106164515019,
      "val_eer": 0.0
    },
    {
      "epoch": 24,
      "loss": 0.011090109590440989,
      "val_eer": 0.0
    },
    {
      "epoch": 25,
      "loss": 0.007615359593182802,
      "val_eer": 0.0
    },
    {
      "epoch": 26,
      "loss": 0.009345298074185849,
      "val_eer": 0.0
    },
    {
      "epoch": 27,
      "loss": 0.005927833635360003,
      "val_eer": 0.0
    },
    {
      "epoch": 28,
      "loss": 0.006189444102346897,
      "val_eer": 0.0
    },
    {
      "epoch": 29,
      "loss": 0.005500974785536528,
      "val_eer": 0.0
    },
    {
      "epoch": 30,
      "loss": 0.04189368300139904,
      "val_eer": 0.0
    },
    {
      "epoch": 31,
      "loss": 0.00742073506116867,
      "val_eer": 0.0
    },
    {
      "epoch": 32,
      "loss": 0.01599881462752819,
      "val_eer": 0.0
    },
    {
      "epoch": 33,
      "loss": 0.007701207743957638,
      "val_eer": 0.0
    },
    {
      "epoch": 34,
      "loss": 0.017313886620104312,
      "val_eer": 0.0
    },
    {
      "epoch": 35,
      "loss": 0.006583171337842942,
      "val_eer": 0.0
    },
    {
      "epoch": 36,
      "loss": 0.004527183342725038,
      "val_eer": 0.0
    },
    {
      "epoch": 37,
      "loss": 0.006930694915354252,
      "val_eer": 0.0
    },
    {
      "epoch": 38,
      "loss": 0.006904072407633066,
      "val_eer": 0.0
    },
    {
      "epoch": 39,
      "loss": 0.007177800964564085,
      "val_eer": 0.0
    },
    {
      "epoch": 40,
      "loss": 0.008572108019143343,
      "val_eer": 0.0
    },
    {
      "epoch": 41,
      "loss": 0.007470996398478746,
      "val_eer": 0.0
    },
    {
      "epoch": 42,
      "loss": 0.00874103233218193,
      "val_eer": 0.0
    },
    {
      "epoch": 43,
      "loss": 0.00566038335673511,
      "val_eer": 0.0
    },
    {
      "epoch": 44,
      "loss": 0.010202310793101788,
      "val_eer": 0.0
    },
    {
      "epoch": 45,
      "loss": 0.005263715796172619,
      "val_eer": 0.0
    },
    {
      "epoch": 46,
      "loss": 0.0059147872496396305,
      "val_eer": 0.0
    },
    {
      "epoch": 47,
      "loss": 0.005741218756884337,
      "val_eer": 0.0
    },
    {
      "epoch": 48,
      "loss": 0.016834354680031537,
      "val_eer": 0.0
    },
    {
      "epoch": 49,
      "loss": 0.005838137492537499,
      "val_eer": 0.0
    },
    {
      "epoch": 50,
      "loss": 0.00535645317286253,
      "val_eer": 0.0
    }
  ]
}